secretconf/__init__.py
tests/__init__.py
tests/test_basic.py
tests/test_properties.py
secretconf-0.1.2.dist-info/LICENSE
secretconf-0.1.2.dist-info/METADATA
secretconf-0.1.2.dist-info/WHEEL
secretconf-0.1.2.dist-info/entry_points.txt
secretconf-0.1.2.dist-info/top_level.txt
secretconf-0.1.2.dist-info/RECORD
