Metadata-Version: 2.1
Name: secretconf
Version: 0.1.2
Summary: manage your secrets and configurations easily
Home-page: https://github.com/xmonader/secretconf
Author: Ahmed Youssef
Author-email: xmonader@gmail.com
License: UNKNOWN
Platform: UNKNOWN
Classifier: Development Status :: 2 - Pre-Alpha
Classifier: Programming Language :: Python
Classifier: Programming Language :: Python :: 2
Classifier: Programming Language :: Python :: 2.7
Classifier: Programming Language :: Python :: 3
Classifier: Programming Language :: Python :: 3.4
Classifier: Programming Language :: Python :: 3.5
